fastchange/__init__.py
fastchange/penalties.py
fastchange/costs/__init__.py
fastchange/costs/base.py
fastchange/costs/emp.py
fastchange/costs/exp.py
fastchange/costs/gamma.py
fastchange/costs/normal.py
fastchange/costs/poisson.py
fastchange/r/__init__.py
fastchange/r/r.py
fastchange/seg/__init__.py
fastchange/seg/amoc.py
fastchange/seg/base.py
fastchange/seg/binseg.py
fastchange/seg/pelt.py
fastchange-1.0.2.dist-info/LICENSE
fastchange-1.0.2.dist-info/METADATA
fastchange-1.0.2.dist-info/WHEEL
fastchange-1.0.2.dist-info/top_level.txt
fastchange-1.0.2.dist-info/RECORD
