Metadata-Version: 2.1
Name: fastchange
Version: 1.0.2
Summary: Fast change point detection in Python
Author: Jacob Gursky
Author-email: gurskyjacob@gmail.com
License: UNKNOWN
Platform: UNKNOWN
License-File: LICENSE
Requires-Dist: numpy
Requires-Dist: numba
Provides-Extra: r
Requires-Dist: rpy2 ; extra == 'r'
Provides-Extra: svml
Requires-Dist: icc-rt ; extra == 'svml'
